pyserverless/__init__.py
pyserverless/auth.py
pyserverless/clientless.py
pyserverless/const.py
pyserverless/main.py
pyserverless/serverless.py
pyserverless/apps/__init__.py
pyserverless/apps/bird.py
pyserverless/apps/imagehosting.py
pyserverless/apps/message_scheduler.py
pyserverless/apps/mstdn.py
pyserverless/apps/rabbitmq.py
pyserverless/apps/twitter.py
pyserverless/bases/__init__.py
pyserverless-0.0.19.dist-info/METADATA
pyserverless-0.0.19.dist-info/WHEEL
pyserverless-0.0.19.dist-info/top_level.txt
pyserverless-0.0.19.dist-info/RECORD
